LICENSE
NEWS
README
TODO
__init__.py
actions.py
cleanimporter.py
create_mudlib.py
delegates.py
events.py
morelimiter.py
multimethod.py
nvt.py
objects.py
orderedset.py
rooms.py
rungrail.py
server.py
setup.py
strutils.py
telnet.py
ticks.py
utils.py
utils_for_testing.py
./__init__.py
./actions.py
./cleanimporter.py
./create_mudlib.py
./delegates.py
./events.py
./morelimiter.py
./multimethod.py
./nvt.py
./objects.py
./orderedset.py
./rooms.py
./rungrail.py
./server.py
./strutils.py
./telnet.py
./ticks.py
./utils.py
./utils_for_testing.py
actiondefs/__init__.py
actiondefs/commands.py
actiondefs/core.py
actiondefs/deaf.py
actiondefs/emote.py
actiondefs/emotefile.txt
actiondefs/helpfiles.py
actiondefs/login.py
actiondefs/logoff.py
actiondefs/look.py
actiondefs/more.py
actiondefs/says.py
actiondefs/setting.py
actiondefs/system.py
actiondefs/targetting.py
actiondefs/who.py
actiondefs/test/test_commands.py
actiondefs/test/test_core.py
actiondefs/test/test_deaf.py
actiondefs/test/test_emote.py
actiondefs/test/test_look.py
actiondefs/test/test_more.py
actiondefs/test/test_says.py
actiondefs/test/test_setting.py
actiondefs/test/test_system.py
actiondefs/test/test_targetting.py
actiondefs/test/test_who.py
doc/architecture.rst
doc/builddocs.py
doc/docutils.conf
doc/emotefile.rst
doc/grail.svg
doc/informationflow.dot
doc/template.txt
doc/utils.py.rst
doc/whatis.rst
grailmud.egg-info/PKG-INFO
grailmud.egg-info/SOURCES.txt
grailmud.egg-info/dependency_links.txt
grailmud.egg-info/requires.txt
grailmud.egg-info/top_level.txt
npcs/__init__.py
npcs/chatty.py
npcs/elizaimpl.py
test/test_cleanimporter.py
test/test_events.py
test/test_morelimiter.py
test/test_multimethod.py
test/test_nvt.py
test/test_objects.py
test/test_orderedset.py
test/test_rooms.py
test/test_strutils.py
test/test_telnet.py
test/test_ticks.py
test/test_utils.py
