Metadata-Version: 1.0
Name: grailmud
Version: 0.1a3
Summary: A Python MUD server
Home-page: http://code.google.com/p/grailmud/
Author: Sam Pointon
Author-email: free.condiments@gmail.com
License: GNU GPL
Keywords: mud server game mmorpg text adventure
Platform: UNKNOWN
Classifier: License :: OSI Approved :: GNU General Public License (GPL)
Classifier: Operating System :: OS Independent
Classifier: Programming Language :: Python
Classifier: Topic :: Communications :: Chat
Classifier: Topic :: Games/Entertainment :: Multi-User Dungeons (MUD)
Classifier: Development Status :: 2 - Pre-Alpha
